ofunctions.random-0.4.0-py3.12-nspkg.pth
ofunctions/random/__init__.py
ofunctions.random-0.4.0.dist-info/LICENSE
ofunctions.random-0.4.0.dist-info/METADATA
ofunctions.random-0.4.0.dist-info/WHEEL
ofunctions.random-0.4.0.dist-info/namespace_packages.txt
ofunctions.random-0.4.0.dist-info/top_level.txt
ofunctions.random-0.4.0.dist-info/RECORD
